gp_cross_factor/__init__.py
gp_cross_factor/_program.py
gp_cross_factor/fitness.py
gp_cross_factor/functions.py
gp_cross_factor/genetic.py
gp_cross_factor/more_functions.py
gp_cross_factor/utils.py
gp_cross_factor-1.0.2.dist-info/LICENSE
gp_cross_factor-1.0.2.dist-info/METADATA
gp_cross_factor-1.0.2.dist-info/WHEEL
gp_cross_factor-1.0.2.dist-info/top_level.txt
gp_cross_factor-1.0.2.dist-info/RECORD
